rye_tui/__init__.py
rye_tui/app.py
rye_tui/cli_parser.py
rye_tui/config.py
rye_tui/constants.py
rye_tui/tooltips.py
rye_tui/tui.py
rye_tui/utils.py
rye_tui/assets/modal_screens.css
rye_tui/assets/tui.css
rye_tui/components/config_tab.py
rye_tui/components/general_tab.py
rye_tui/components/helper_widgets.py
rye_tui/components/mainframe.py
rye_tui/components/modals.py
rye_tui/components/projects_tab.py
rye_tui/static/rye_image.jpg
rye_tui-0.5.1.dist-info/METADATA
rye_tui-0.5.1.dist-info/WHEEL
rye_tui-0.5.1.dist-info/entry_points.txt
rye_tui-0.5.1.dist-info/licenses/LICENSE.txt
rye_tui-0.5.1.dist-info/RECORD
