Metadata-Version: 2.3
Name: rye-tui
Version: 0.5.1
Summary: Rye meets Textual. Manage your python projects with a Tui
Project-URL: Repository, https://github.com/Zaloog/rye-tui
Project-URL: Changelog, https://github.com/Zaloog/rye-tui/blob/main/CHANGELOG.md
Author-email: Zaloog <gramslars@gmail.com>
License: MIT
License-File: LICENSE.txt
Keywords: python,rye,textual,tui
Classifier: Development Status :: 3 - Alpha
Classifier: License :: OSI Approved :: MIT License
Classifier: Operating System :: OS Independent
Classifier: Programming Language :: Python
Classifier: Programming Language :: Python :: 3 :: Only
Classifier: Programming Language :: Python :: 3.8
Classifier: Programming Language :: Python :: 3.9
Classifier: Programming Language :: Python :: 3.10
Classifier: Programming Language :: Python :: 3.11
Classifier: Programming Language :: Python :: 3.12
Requires-Python: >=3.8
Requires-Dist: platformdirs>=4.2.2
Requires-Dist: rich-pixels>=3.0.1
Requires-Dist: textual>=0.70.0
Requires-Dist: tomlkit>=0.12.5
